capybarish/__init__.py
capybarish/communication.py
capybarish/config_manager.py
capybarish/dashboard_server.py
capybarish/data_struct.py
capybarish/interface.py
capybarish/interpreter.py
capybarish/kbhit.py
capybarish/plugin_system.py
capybarish/py.typed
capybarish/service_registry.py
capybarish/utils.py
capybarish/natnet/DataDescriptions.py
capybarish/natnet/MoCapData.py
capybarish/natnet/NatNetClient.py
capybarish/natnet/PythonSample.py
capybarish-0.1.0.dist-info/licenses/LICENSE
plugins/__init__.py
plugins/imu_processor.py
plugins/optitrack_source.py
capybarish-0.1.0.dist-info/METADATA
capybarish-0.1.0.dist-info/WHEEL
capybarish-0.1.0.dist-info/entry_points.txt
capybarish-0.1.0.dist-info/top_level.txt
capybarish-0.1.0.dist-info/RECORD
